MANIFEST.in
README.md
requirements.txt
setup.py
mkrunner/__init__.py
mkrunner/__main__.py
mkrunner/cli.py
mkrunner/cli.spec
mkrunner/client.py
mkrunner/compat.py
mkrunner/exceptions.py
mkrunner/loader.py
mkrunner/log.py
mkrunner/make.py
mkrunner/models.py
mkrunner/parser.py
mkrunner/response.py
mkrunner/runner.py
mkrunner/scaffold.py
mkrunner/testcase.py
mkrunner/utils.py
mkrunner.egg-info/PKG-INFO
mkrunner.egg-info/SOURCES.txt
mkrunner.egg-info/dependency_links.txt
mkrunner.egg-info/entry_points.txt
mkrunner.egg-info/requires.txt
mkrunner.egg-info/top_level.txt
mkrunner/app/__init__.py
mkrunner/app/main.py
mkrunner/app/routers/__init__.py
mkrunner/app/routers/debug.py
mkrunner/app/routers/debugtalk.py
mkrunner/app/routers/deps.py
mkrunner/builtin/__init__.py
mkrunner/builtin/comparators.py
mkrunner/builtin/functions.py
mkrunner/ext/__init__.py
mkrunner/ext/har2case/__init__.py
mkrunner/ext/har2case/core.py
mkrunner/ext/har2case/utils.py
mkrunner/ext/locust/__init__.py
mkrunner/ext/locust/locustfile.py
mkrunner/ext/uploader/__init__.py