Metadata-Version: 2.1
Name: mkrunner
Version: 1.1.1
Summary: One-stop solution for HTTP(S) testing.
Home-page: https://github.com/httprunner/httprunner
Author: zhushiwei
Author-email: 1396516176@qq.com
License: UNKNOWN
Platform: UNKNOWN
Requires-Python: >=3.6,<4.0
Provides-Extra: locust
Provides-Extra: upload
Provides-Extra: allure
